iris/__init__.py
iris/__main__.py
iris/api/__init__.py
iris/api/files.py
iris/config/__init__.py
iris/config/flask.py
iris/models/__init__.py
iris/models/config.py
iris/models/db.py
iris/models/files.py
iris/public/css/main.css
iris/public/img/favicon.ico
iris/public/img/favicon.png
iris/public/img/iris-logo-blue.png
iris/public/img/iris-logo-white.png
iris/public/js/modules/.gitkeep
iris/public/js/modules/main.js
iris/routes/__init__.py
iris/routes/api.py
iris/routes/general.py
iris/templates/base.html
iris/templates/general/home.html
iris/templates/partials/navbar.html
iris/utils/__init__.py
iris/utils/files.py
iris_image_labelling-0.1.0.dist-info/LICENCE.md
iris_image_labelling-0.1.0.dist-info/METADATA
iris_image_labelling-0.1.0.dist-info/WHEEL
iris_image_labelling-0.1.0.dist-info/entry_points.txt
iris_image_labelling-0.1.0.dist-info/top_level.txt
iris_image_labelling-0.1.0.dist-info/RECORD
