Metadata-Version: 2.1
Name: iris-image-labelling
Version: 0.1.0
Summary: Browser based platform for labelling data
Home-page: https://www.github.com/ismailuddin/iris
Author: Ismail Uddin
Author-email: ismail.sameeuddin@gmail.com
License: MIT
Platform: UNKNOWN
Classifier: License :: OSI Approved :: MIT License
Classifier: Programming Language :: Python
Classifier: Programming Language :: Python :: 3.6
Classifier: Programming Language :: Python :: 3.7
Requires-Dist: click
Requires-Dist: Flask
Requires-Dist: Flask-SQLAlchemy
Requires-Dist: itsdangerous
Requires-Dist: Jinja2
Requires-Dist: MarkupSafe
Requires-Dist: SQLAlchemy
Requires-Dist: tqdm
Requires-Dist: Werkzeug
